formiko/__init__.py
formiko/__main__.py
formiko/application.py
formiko/dialogs.py
formiko/editor_actions.py
formiko/menu.py
formiko/preferences.py
formiko/renderer.py
formiko/shortcuts.py
formiko/sourceview.py
formiko/status_menu.py
formiko/user.py
formiko/vim.py
formiko/widgets.py
formiko/window.py
formiko-1.5.0.data/data/share/applications/formiko-vim.desktop
formiko-1.5.0.data/data/share/applications/formiko.desktop
formiko-1.5.0.data/data/share/doc/formiko/AUTHORS
formiko-1.5.0.data/data/share/doc/formiko/COPYING
formiko-1.5.0.data/data/share/doc/formiko/ChangeLog
formiko-1.5.0.data/data/share/doc/formiko/README.rst
formiko-1.5.0.data/data/share/formiko/icons/formiko.svg
formiko-1.5.0.data/data/share/icons/hicolor/128x128/apps/formiko.png
formiko-1.5.0.data/data/share/icons/hicolor/16x16/apps/formiko.png
formiko-1.5.0.data/data/share/icons/hicolor/22x22/apps/formiko.png
formiko-1.5.0.data/data/share/icons/hicolor/24x24/apps/formiko.png
formiko-1.5.0.data/data/share/icons/hicolor/256x256/apps/formiko.png
formiko-1.5.0.data/data/share/icons/hicolor/32x32/apps/formiko.png
formiko-1.5.0.data/data/share/icons/hicolor/48x48/apps/formiko.png
formiko-1.5.0.data/data/share/icons/hicolor/512x512/apps/formiko.png
formiko-1.5.0.data/data/share/icons/hicolor/64x64/apps/formiko.png
formiko-1.5.0.data/data/share/icons/hicolor/scalable/apps/formiko.svg
formiko-1.5.0.data/data/share/man/man1/formiko-vim.1.gz
formiko-1.5.0.data/data/share/man/man1/formiko.1.gz
formiko-1.5.0.data/data/share/metainfo/formiko.metainfo.xml
formiko-1.5.0.dist-info/AUTHORS
formiko-1.5.0.dist-info/COPYING
formiko-1.5.0.dist-info/METADATA
formiko-1.5.0.dist-info/WHEEL
formiko-1.5.0.dist-info/entry_points.txt
formiko-1.5.0.dist-info/top_level.txt
formiko-1.5.0.dist-info/RECORD
