Metadata-Version: 2.1
Name: formiko
Version: 1.5.0
Summary: Formiko is reStructuredText and MarkDown editor and live previewer.
Home-page: https://github.com/ondratu/formiko
Author: Ondrej Tuma
Author-email: mcbig@zeropage.cz
License: BSD
Keywords: doc,html,rst,docutils,md,markdown,editor
Classifier: Development Status :: 5 - Production/Stable
Classifier: Environment :: X11 Applications :: GTK
Classifier: Intended Audience :: Developers
Classifier: Intended Audience :: End Users/Desktop
Classifier: License :: OSI Approved :: BSD License
Classifier: Natural Language :: English
Classifier: Operating System :: OS Independent
Classifier: Programming Language :: Python :: 3
Classifier: Topic :: Documentation
Classifier: Topic :: Software Development :: Documentation
Classifier: Topic :: Text Editors :: Documentation
Classifier: Topic :: Text Editors :: Text Processing
Classifier: Topic :: Text Processing
Classifier: Topic :: Text Processing :: Markup
Classifier: Topic :: Text Processing :: Markup :: HTML
Classifier: Topic :: Utilities
Requires: docutils (>= 0.12)
Requires: python_gi
Requires: webkit2
Requires: gtksourceview
License-File: COPYING
License-File: AUTHORS
Requires-Dist: docutils>=0.12
